zapscrapper/errors.py
zapscrapper/utils.py
zapscrapper/zap_imoveis.py
zapscrapper-0.0.7.dist-info/DESCRIPTION.rst
zapscrapper-0.0.7.dist-info/METADATA
zapscrapper-0.0.7.dist-info/RECORD
zapscrapper-0.0.7.dist-info/WHEEL
zapscrapper-0.0.7.dist-info/metadata.json
zapscrapper-0.0.7.dist-info/top_level.txt
