Metadata-Version: 2.0
Name: zapscrapper
Version: 0.0.7
Summary: This is a package to make webscrappng on zapimoveis.com.br
Home-page: UNKNOWN
Author: Eduardo M. de Morais
Author-email: emdemor415@gmail.com
License: MIT License
Keywords: webscrapping,imoveis
Platform: UNKNOWN
Requires-Dist: BeautifulSoup4 (>=4.9.0)
Requires-Dist: boto3 (>=1.17.59)
Requires-Dist: sqlalchemy (>=1.3.20)
Requires-Dist: tqdm (>=4.59.0)
Requires-Dist: pandas (>=1.1.5)
